secpat2gf/__init__.py
secpat2gf/__main__.py
secpat2gf/secpat2gf.py
secpat2gf-1.1.0.dist-info/METADATA
secpat2gf-1.1.0.dist-info/WHEEL
secpat2gf-1.1.0.dist-info/entry_points.txt
secpat2gf-1.1.0.dist-info/licenses/LICENSE
secpat2gf-1.1.0.dist-info/RECORD
