Metadata-Version: 2.1
Name: secpat2gf
Version: 1.1.0
Summary: convert secret patterns to gf compatible
Project-URL: Homepage, https://github.com/dwisiswant0/secpat2gf
Project-URL: Bug Tracker, https://github.com/dwisiswant0/secpat2gf/issues
Author-email: Dwi Siswanto <me@dw1.io>
License: MIT License
License-File: LICENSE
Keywords: feed,reader,tutorial
Classifier: License :: OSI Approved :: MIT License
Classifier: Programming Language :: Python
Classifier: Programming Language :: Python :: 3
Classifier: Topic :: Security
Classifier: Topic :: Utilities
Requires-Python: >=3.6
Requires-Dist: pyyaml>=6.0
Requires-Dist: requests>=2.25.1
